{
  "main": {
    "id": "116b2153ebf498a7",
    "type": "split",
    "children": [
      {
        "id": "5a123877c2b69b70",
        "type": "tabs",
        "children": [
          {
            "id": "b4c6847e1043a61f",
            "type": "leaf",
            "state": {
              "type": "markdown",
              "state": {
                "file": "Econ 236B/Lecture 7.md",
                "mode": "source",
                "source": false
              },
              "icon": "lucide-file",
              "title": "Lecture 7"
            }
          }
        ]
      }
    ],
    "direction": "vertical"
  },
  "left": {
    "id": "05f6517ae7b9a182",
    "type": "split",
    "children": [
      {
        "id": "b1fd783d517b243d",
        "type": "tabs",
        "children": [
          {
            "id": "8dd6a8bcce27e5bd",
            "type": "leaf",
            "state": {
              "type": "file-explorer",
              "state": {
                "sortOrder": "alphabetical",
                "autoReveal": false
              },
              "icon": "lucide-folder-closed",
              "title": "文件列表"
            }
          },
          {
            "id": "689d9025b4d9f476",
            "type": "leaf",
            "state": {
              "type": "search",
              "state": {
                "query": "oscil",
                "matchingCase": false,
                "explainSearch": false,
                "collapseAll": false,
                "extraContext": false,
                "sortOrder": "alphabetical"
              },
              "icon": "lucide-search",
              "title": "搜索"
            }
          },
          {
            "id": "7c82c92993a49841",
            "type": "leaf",
            "state": {
              "type": "bookmarks",
              "state": {},
              "icon": "lucide-bookmark",
              "title": "书签"
            }
          }
        ]
      }
    ],
    "direction": "horizontal",
    "width": 201.50271224975586,
    "collapsed": true
  },
  "right": {
    "id": "707048cafdbf033b",
    "type": "split",
    "children": [
      {
        "id": "a3ac5f72aa7eb2bc",
        "type": "tabs",
        "children": [
          {
            "id": "bd44574480680ae2",
            "type": "leaf",
            "state": {
              "type": "backlink",
              "state": {
                "file": "Practice 1.md",
                "collapseAll": false,
                "extraContext": false,
                "sortOrder": "alphabetical",
                "showSearch": false,
                "searchQuery": "",
                "backlinkCollapsed": false,
                "unlinkedCollapsed": true
              },
              "icon": "links-coming-in",
              "title": "Practice 1 的反向链接列表"
            }
          },
          {
            "id": "8d20c73e3cfdf4ed",
            "type": "leaf",
            "state": {
              "type": "outgoing-link",
              "state": {
                "file": "Practice 1.md",
                "linksCollapsed": false,
                "unlinkedCollapsed": true
              },
              "icon": "links-going-out",
              "title": "Practice 1 的出链列表"
            }
          },
          {
            "id": "a2a37f5292e05716",
            "type": "leaf",
            "state": {
              "type": "tag",
              "state": {
                "sortOrder": "frequency",
                "useHierarchy": true,
                "showSearch": false,
                "searchQuery": ""
              },
              "icon": "lucide-tags",
              "title": "标签"
            }
          },
          {
            "id": "0e141defb7b02e92",
            "type": "leaf",
            "state": {
              "type": "outline",
              "state": {
                "file": "未命名.md"
              },
              "icon": "lucide-list",
              "title": "未命名 的大纲"
            }
          },
          {
            "id": "4d0abe5cc400e4a2",
            "type": "leaf",
            "state": {
              "type": "git-view",
              "state": {},
              "icon": "git-pull-request",
              "title": "Source Control"
            }
          },
          {
            "id": "277f2675e8983760",
            "type": "leaf",
            "state": {
              "type": "pdf",
              "state": {
                "file": "Math 104/Ch4.pdf",
                "page": 8,
                "left": -4,
                "top": 670,
                "zoom": 1.33
              },
              "icon": "lucide-file-text",
              "title": "Ch4"
            }
          },
          {
            "id": "fce55a78e6a3742f",
            "type": "leaf",
            "state": {
              "type": "pdf",
              "state": {
                "file": "Math 104/Ch5.pdf",
                "page": 10,
                "left": 62,
                "top": 718,
                "zoom": 1.2
              },
              "icon": "lucide-file-text",
              "title": "Ch5"
            }
          },
          {
            "id": "fd3ade4da902a041",
            "type": "leaf",
            "state": {
              "type": "pdf",
              "state": {
                "file": "Econ 236B/Lecture_7.pdf",
                "page": 38,
                "left": -13,
                "top": 112,
                "zoom": 1.2187378043537218
              },
              "icon": "lucide-file-text",
              "title": "Lecture_7"
            }
          }
        ],
        "currentTab": 4
      }
    ],
    "direction": "horizontal",
    "width": 777.5
  },
  "left-ribbon": {
    "hiddenItems": {
      "pdf-plus:PDF++: Toggle auto-copy": false,
      "pdf-plus:PDF++: Toggle auto-focus": false,
      "pdf-plus:PDF++: Toggle auto-paste": false,
      "markdown-importer:打开 Markdown 格式转换器": false,
      "switcher:打开快速切换": false,
      "graph:查看关系图谱": false,
      "canvas:新建白板": false,
      "daily-notes:打开/创建今天的日记": false,
      "templates:插入模板": false,
      "command-palette:打开命令面板": false,
      "obsidian-git:Open Git source control": false,
      "translate:Open translation view": false
    }
  },
  "active": "fd3ade4da902a041",
  "lastOpenFiles": [
    "Econ 236B/Lecture 7.md",
    "Econ 236B/Lecture_7.pdf",
    "Math 104/Lecture 5.md",
    "Math 104/Ch5.pdf",
    "Math 104/Ch4.pdf",
    "Math 104/Lecture 4.md",
    "Math 104/Midterm Review.md",
    "Math 104/Practice 1.md",
    "Math 104/Lecture 3b.md",
    "Math 128A/Lecture 8.md",
    "Screenshot 2025-03-15 at 18.04.25.png",
    "Screenshot 2025-03-15 at 17.42.48.png",
    "Screenshot 2025-03-15 at 17.41.00.png",
    "Screenshot 2025-03-15 at 17.37.42.png",
    "Screenshot 2025-03-15 at 17.37.15.png",
    "Screenshot 2025-03-15 at 17.08.09.png",
    "Screenshot 2025-03-15 at 16.30.19.png",
    "Math 128A/Lecture 7.md",
    "Screenshot 2025-03-15 at 15.23.36.png",
    "Screenshot 2025-03-15 at 15.22.57.png",
    "Screenshot 2025-03-15 at 15.19.44.png",
    "Econ 236B/The Intertemporal Keynesian Cross.md",
    "Econ 236B/Monetary Policy According to HANK.md",
    "Math 128B/Part II.md",
    "Ch4.pdf",
    "Econ 236B/Lecture_6b.pdf",
    "Econ 236B",
    "Math 128B",
    "Math 128A/Lecture 6.md",
    "Math 128A/Lecture 5.md",
    "Math 128A",
    "欢迎.md",
    "2025-03-05.md",
    "Math 104",
    "未命名.canvas"
  ]
}